[
    {
        "section_no": "1",
        "section_name": "LIVE ANIMALS; ANIMAL PRODUCTS",
        "section_desc": ""
    },
    {
        "section_no": "2",
        "section_name": "VEGETABLE PRODUCTS",
        "section_desc": ""
    },
    {
        "section_no": "3",
        "section_name": "ANIMAL OR VEGETABLE FATS AND OILS AND THEIR CLEAVAGE PRODUCTS;PREPARED EDIBLE FATS; ANIMAL OR VEGETABLE WAXES",
        "section_desc": ""
    },
    {
        "section_no": "4",
        "section_name": "PREPARED FOODSTUFFS; BEVERAGES, SPIRITS AND VINEGAR; TOBACCO AND MANUFACTURED TOBACCO SUBSTITUTES",
        "section_desc": ""
    },
    {
        "section_no": "5",
        "section_name": "MINERAL PRODUCTS",
        "section_desc": ""
    },
    {
        "section_no": "6",
        "section_name": "PRODUCTS OF THE CHEMICAL OR ALLIED INDUSTRIES",
        "section_desc": ""
    },
    {
        "section_no": "7",
        "section_name": "PLASTICS AND ARTICLES THEREOF; RUBBER AND ARTICLES THEREOF",
        "section_desc": ""
    },
    {
        "section_no": "8",
        "section_name": "RAW HIDES AND SKINS, LEATHER, FURSKINS AND ARTICLES THEREOF; SADDLERY AND HARNESS; TRAVEL GOODS,HANDBAGS AND SIMILAR CONTAINERS; ARTICLES OF ANIMAL GUT (OTHER THAN SILK-WORM GUT)",
        "section_desc": ""
    },
    {
        "section_no": "9",
        "section_name": "WOOD AND ARTICLES OF WOOD; WOOD CHARCOAL; CORK AND ARTICLES OF CORK; MANUFACTURES OF STRAW, OF ESPARTO OR OF OTHER PLAITING MATERIALS; BASKETWARE AND WICKERWORK",
        "section_desc": ""
    },
    {
        "section_no": "10",
        "section_name": "PULP OF WOOD OR OF OTHER FIBROUS CELLULOSIC MATERIAL; RECOVERED (WASTE AND SCRAP) PAPER OR PAPERBOARD;PAPER AND PAPERBOARD AND ARTICLES THEREOF",
        "section_desc": ""
    },
    {
        "section_no": "11",
        "section_name": "TEXTILES AND TEXTILE ARTICLES",
        "section_desc": ""
    },
    {
        "section_no": "12",
        "section_name": "FOOTWEAR, HEADGEAR, UMBRELLAS, SUN UMBRELLAS, WALKING-STICKS, SEAT-STICKS, WHIPS, RIDING-CROPS AND PARTS THEREOF; PREPARED FEATHERS AND ARTICLES MADE THEREWITH; ARTIFICIAL FLOWERS; ARTICLES OF HUMAN HAIR",
        "section_desc": ""
    },
    {
        "section_no": "13",
        "section_name": "ARTICLES OF STONE, PLASTER, CEMENT, ASBESTOS, MICA OR SIMILAR MATERIALS; GLASS AND GLASSWARE",
        "section_desc": ""
    },
    {
        "section_no": "14",
        "section_name": "NATURAL OR CULTURED PEARLS, PRECIOUS OR SEMI-PRECIOUS STONES, PRECIOUS METALS, METALS CLAD WITH PRECIOUS METAL,AND ARTICLES THEREOF; IMITATION JEWELLERY; COIN",
        "section_desc": ""
    },
    {
        "section_no": "15",
        "section_name": "BASE METALS AND ARTICLES OF BASE METAL",
        "section_desc": ""
    },
    {
        "section_no": "16",
        "section_name": "MACHINERY AND MECHANICAL APPLIANCES; ELECTRICAL EQUIPMENT; PARTS THEREOF;SOUND RECORDERS AND REPRODUCERS, TELEVISION IMAGE AND SOUND RECORDERS AND REPRODUCERS, AND PARTS AND ACCESSORIES OF SUCH ARTICLES",
        "section_desc": ""
    },
    {
        "section_no": "17",
        "section_name": "VEHICLES, AlRCRAFT, VESSELS AND ASSOCIATED TRANSPORT EQUIPMENT",
        "section_desc": ""
    },
    {
        "section_no": "18",
        "section_name": "OPTICAL, PHOTOGRAPHIC, CINEMATOGRAPHIC, MEASURING, CHECKING, PRECISION, MEDICAL OR SURGICAL INSTRUMENTS AND APPARATUS; CLOCKS AND WATCHES; MUSICAL INSTRUMENTS; PARTS AND ACCESSORIES THEREOF",
        "section_desc": ""
    },
    {
        "section_no": "19",
        "section_name": "ARMS AND AMMUNITION; PARTS AND ACCESSORIES THEREOF",
        "section_desc": ""
    },
    {
        "section_no": "20",
        "section_name": "MISC LLANEOUS MANUFACTURED ARTICLES",
        "section_desc": ""
    },
    {
        "section_no": "21",
        "section_name": "WORKS OF ART, COLLECTORS' PIECES AND ANTIQUES",
        "section_desc": ""
    }
]